{
  "application programming interface": ["API"],
  "artificial intelligence": ["AI"],
  "continuous integration": ["CI"],
  "continuous delivery": ["CD"],
  "continuous deployment": ["CD"],
  "ci/cd": ["continuous integration", "continuous delivery", "continuous deployment"],
  "content delivery network": ["CDN"],
  "cross-site request forgery": ["CSRF", "cross site request forgery"],
  "cross-site scripting": ["XSS", "cross site scripting"],
  "data loss prevention": ["DLP"],
  "distributed denial of service": ["DDoS", "DDOS"],
  "domain name system": ["DNS"],
  "encryption": ["enc"],
  "garbage collection": ["GC"],
  "identity and access management": ["IAM"],
  "infrastructure as code": ["IaC"],
  "internet protocol": ["IP"],
  "java virtual machine": ["JVM"],
  "javascript": ["JS"],
  "json": ["JavaScript Object Notation"],
  "key performance indicator": ["KPI"],
  "kubernetes": ["K8s"],
  "machine learning": ["ML"],
  "message queue": ["MQ"],
  "natural language processing": ["NLP"],
  "object oriented programming": ["OOP"],
  "oauth": ["OAuth2", "OAuth 2.0"],
  "public key infrastructure": ["PKI"],
  "quality assurance": ["QA"],
  "random access memory": ["RAM"],
  "read only memory": ["ROM"],
  "representational state transfer": ["REST"],
  "secure sockets layer": ["SSL"],
  "service level agreement": ["SLA"],
  "service level indicator": ["SLI"],
  "service level objective": ["SLO"],
  "single sign-on": ["SSO"],
  "structured query language": ["SQL"],
  "transport layer security": ["TLS"],
  "user experience": ["UX"],
  "user interface": ["UI"],
  "virtual private network": ["VPN"]
}
